mirror_gitblit/GitblitMirror.py
mirror_gitblit/__init__.py
mirror_gitblit/__version__.py
mirror_gitblit-0.2.0.dist-info/METADATA
mirror_gitblit-0.2.0.dist-info/WHEEL
mirror_gitblit-0.2.0.dist-info/top_level.txt
mirror_gitblit-0.2.0.dist-info/RECORD
