Metadata-Version: 2.1
Name: mirror-gitblit
Version: 0.2.0
Summary: Tool to mirror repositories of a gitblit server
Home-page: https://mathcoach.htwsaar.de
Author: Hong-Phuc Bui
Author-email: hong-phuc.bui@htwsaar.de
License: UNKNOWN
Platform: UNKNOWN
